conf/config.ini.sample
conf/log.ini.sample
method/__init__.py
method/file_create.py
method/mongodb_base.py
method/mongodb_dump.py
method/mongodb_import.py
mongodbtool.py
mongo_tool-0.0.1.dist-info/LICENSE
mongo_tool-0.0.1.dist-info/METADATA
mongo_tool-0.0.1.dist-info/WHEEL
mongo_tool-0.0.1.dist-info/entry_points.txt
mongo_tool-0.0.1.dist-info/RECORD
