Metadata-Version: 2.1
Name: mongo-tool
Version: 0.0.1
Summary: Mongodb数据操作工具
Home-page: https://github.com/Zcxx0322/mongodb-tool
Author: Zcx
Author-email: colampszcx@gmail.com
Requires-Python: >=3.8.5,<4.0.0
Classifier: Intended Audience :: Developers
Classifier: Operating System :: OS Independent
Classifier: Programming Language :: Python
Classifier: Programming Language :: Python :: 3
Classifier: Programming Language :: Python :: 3.9
Classifier: Programming Language :: Python :: 3.10
Classifier: Programming Language :: Python :: 3.11
Classifier: Topic :: System :: System Shells
Requires-Dist: happy-python (>=0.4.7)
Requires-Dist: pymongo (>=4.5.0)
Requires-Dist: pytest (>=7.4.1)
Project-URL: Documentation, https://github.com/Zcxx0322/mongodb-tool
Project-URL: Repository, https://github.com/Zcxx0322/mongodb-tool
